eco2ai/MLTracker.py
eco2ai/__init__.py
eco2ai/data/carbon_index.csv
eco2ai/data/config.txt
eco2ai/data/cpu_names.csv
eco2ai/emission_track.py
eco2ai/tools/__init__.py
eco2ai/tools/tools_cpu.py
eco2ai/tools/tools_gpu.py
eco2ai/tools/tools_ram.py
eco2ai/utils.py
eco2ai-0.3.11.dist-info/LICENSE
eco2ai-0.3.11.dist-info/WHEEL
eco2ai-0.3.11.dist-info/METADATA
eco2ai-0.3.11.dist-info/RECORD
