Metadata-Version: 2.1
Name: eco2ai
Version: 0.3.11
Summary: emission tracking library
Home-page: https://github.com/sb-ai-lab/Eco2AI
Author: AI Lab
Classifier: Development Status :: 3 - Alpha
Classifier: Environment :: Console
Classifier: Intended Audience :: Science/Research
Classifier: Natural Language :: English
Classifier: Operating System :: OS Independent
Classifier: Programming Language :: Python :: 2
Classifier: Programming Language :: Python :: 2.7
Classifier: Programming Language :: Python :: 3
Classifier: Programming Language :: Python :: 3.4
Classifier: Programming Language :: Python :: 3.5
Classifier: Programming Language :: Python :: 3.6
Classifier: Programming Language :: Python :: 3.7
Classifier: Programming Language :: Python :: 3.8
Classifier: Programming Language :: Python :: 3.9
Classifier: Programming Language :: Python :: 3.10
Classifier: Programming Language :: Python :: 3.11
Classifier: Programming Language :: Python :: 3.7
Classifier: Topic :: Scientific/Engineering :: Artificial Intelligence
Classifier: Typing :: Typed
Requires-Dist: APScheduler ; python_version >= "2.7" and python_full_version < "3.0.0" or python_full_version >= "3.5.0" and python_version < "4"
Requires-Dist: pandas (>=1.2.1,<=1.3.5) ; python_full_version >= "3.7.1" and python_version < "3.8"
Requires-Dist: pandas (>=1.4.0) ; python_version >= "3.8"
Requires-Dist: psutil (>=5.9.1)
Requires-Dist: py-cpuinfo ; python_version >= "3.7"
Requires-Dist: pynvml ; python_version >= "3.6"
Requires-Dist: requests ; python_version >= "3.7" and python_version < "4"
Requires-Dist: setuptools
Requires-Dist: tornado ; python_version >= "3.7"
Requires-Dist: tzlocal ; python_version >= "3.6"
Project-URL: Repository, https://github.com/sb-ai-lab/Eco2AI
